pseudonymizer/__init__.py
pseudonymizer/anonymizationSecurityMeasure.py
pseudonymizer/createMappingTable.py
pseudonymizer/extractJoinDatafromDB.py
pseudonymizer/joinTargetTables.py
pseudonymizer/privacyPreservingModels.py
pseudonymizer/pseudonym.py
pseudonymizer/pseudonymUtilityMeasure.py
pseudonymizer/pseudonymizer.py
pseudonymizer/updateEncryptedKeyIntoDB.py
pseudonymizer/cryptocontainers/DBContainer.py
pseudonymizer/cryptocontainers/__init__.py
pseudonymizer/cryptocontainers/bundleKeyTable.py
pseudonymizer/cryptocontainers/bundleMainTable.py
pseudonymizer/cryptocontainers/bundleTables.py
pseudonymizer/cryptocontainers/bundleTargetTable.py
pseudonymizer/deidentificationTechnique/__init__.py
pseudonymizer/deidentificationTechnique/differentialPrivacy.py
pseudonymizer/deidentificationTechnique/equivalentClass.py
pseudonymizer/deidentificationTechnique/gaussiandifferentialPrivacy.py
pseudonymizer/deidentificationTechnique/kAnonymity.py
pseudonymizer/deidentificationTechnique/lDiversity.py
pseudonymizer/deidentificationTechnique/tClosenessFactor.py
pseudonymizer/deidentificationTechnique/tClosenessNumeric.py
pseudonymizer/encryptionPseudonyms/__init__.py
pseudonymizer/encryptionPseudonyms/abstractPreprocessQuery.py
pseudonymizer/encryptionPseudonyms/encrypttoKeyColumn.py
pseudonymizer/encryptionPseudonyms/insertKeyintoMainTable.py
pseudonymizer/encryptionPseudonyms/insertTargetintoMainTable.py
pseudonymizer/encryptionPseudonyms/pyMySQLQuery.py
pseudonymizer/encryptionPseudonyms/updateSerialNumColumn.py
pseudonymizer/examples/__init__.py
pseudonymizer/pseudonymizers/__init__.py
pseudonymizer/pseudonymizers/addressMaskingModule.py
pseudonymizer/pseudonymizers/businessNumMasking.py
pseudonymizer/pseudonymizers/charcategorization.py
pseudonymizer/pseudonymizers/columncategorization.py
pseudonymizer/pseudonymizers/emailMasking.py
pseudonymizer/pseudonymizers/maskingPseudonymizer.py
pseudonymizer/pseudonymizers/microAggregation.py
pseudonymizer-0.1.8.dist-info/LICENSE.txt
pseudonymizer-0.1.8.dist-info/METADATA
pseudonymizer-0.1.8.dist-info/WHEEL
pseudonymizer-0.1.8.dist-info/top_level.txt
pseudonymizer-0.1.8.dist-info/RECORD
