Metadata-Version: 2.1
Name: pseudonymizer
Version: 0.1.8
Summary: pseudonymizer-to-protect-private-personal-data
Home-page: https://github.com/ksydata/pseudonymizer
Author: ksydata
Author-email: ksydata01@gmail.com
License: MIT License
Requires-Python: >3.6
License-File: LICENSE.txt
Requires-Dist: pandas (==1.5.3)
Requires-Dist: PyMySQL (==1.1.0)
Requires-Dist: numpy (==1.22.3)
Requires-Dist: scipy (==1.10.0)
Requires-Dist: setuptools (==63.4.1)
Requires-Dist: prettytable (==3.9.0)
